intouch/__init__.py
intouch/queryset_csv/__init__.py
intouch/queryset_csv/admin.py
intouch/queryset_csv/apps.py
intouch/queryset_csv/shortcuts.py
intouch/queryset_csv/tests.py
intouch/queryset_csv/urls.py
intouch/queryset_csv/views.py
intouch_queryset_csv-0.3.1.dist-info/COPYING
intouch_queryset_csv-0.3.1.dist-info/LICENSE
intouch_queryset_csv-0.3.1.dist-info/METADATA
intouch_queryset_csv-0.3.1.dist-info/WHEEL
intouch_queryset_csv-0.3.1.dist-info/top_level.txt
intouch_queryset_csv-0.3.1.dist-info/RECORD
